MANIFEST.in
README.md
pyproject.toml
setup.cfg
setup.py
jourdanhub/__init__.py
jourdanhub/__main__.py
jourdanhub/_version.py
jourdanhub/app.py
jourdanhub/userapi_handler.py
jourdanhub.egg-info/PKG-INFO
jourdanhub.egg-info/SOURCES.txt
jourdanhub.egg-info/dependency_links.txt
jourdanhub.egg-info/entry_points.txt
jourdanhub.egg-info/not-zip-safe
jourdanhub.egg-info/requires.txt
jourdanhub.egg-info/top_level.txt