Metadata-Version: 2.1
Name: jourdanhub
Version: 0.0.5
Summary: Wrapper for JupyterHub
Home-page: https://github.com/carlosjourdan/jourdanhub
Author: Carlos Jourdan
License: AGPL-3.0
Keywords: JupyterHub,SWAN,CERN
Platform: Linux
Platform: Mac OS X
Classifier: License :: OSI Approved :: GNU Affero General Public License v3
Classifier: Intended Audience :: Developers
Classifier: Intended Audience :: System Administrators
Classifier: Intended Audience :: Science/Research
Classifier: Programming Language :: Python
Classifier: Programming Language :: Python :: 3
